gitsc/__init__.py
gitsc/cli.py
gitsc-1.1.0.dist-info/licenses/LICENSE
gitsc-1.1.0.dist-info/METADATA
gitsc-1.1.0.dist-info/WHEEL
gitsc-1.1.0.dist-info/entry_points.txt
gitsc-1.1.0.dist-info/top_level.txt
gitsc-1.1.0.dist-info/RECORD
