Metadata-Version: 2.4
Name: gitsc
Version: 1.1.0
Summary: AI-powered semantic git commit message generator using Groq's LLaMA models
Home-page: https://github.com/prxdyut/gitsc
Author: Pradyut Das
Author-email: daspradyut516@gmail.com
Project-URL: Bug Tracker, https://github.com/prxdyut/gitsc/issues
Project-URL: Documentation, https://github.com/prxdyut/gitsc#readme
Project-URL: Source Code, https://github.com/prxdyut/gitsc
Keywords: git,commit,semantic,conventional-commits,ai,llm,groq
Classifier: Development Status :: 5 - Production/Stable
Classifier: Environment :: Console
Classifier: Intended Audience :: Developers
Classifier: License :: OSI Approved :: MIT License
Classifier: Operating System :: OS Independent
Classifier: Programming Language :: Python
Classifier: Programming Language :: Python :: 3
Classifier: Programming Language :: Python :: 3.6
Classifier: Programming Language :: Python :: 3.7
Classifier: Programming Language :: Python :: 3.8
Classifier: Programming Language :: Python :: 3.9
Classifier: Programming Language :: Python :: 3.10
Classifier: Programming Language :: Python :: 3.11
Classifier: Topic :: Software Development :: Libraries :: Python Modules
Classifier: Topic :: Software Development :: Version Control
Classifier: Topic :: Software Development :: Version Control :: Git
Classifier: Natural Language :: English
Requires-Python: >=3.6
License-File: LICENSE
Requires-Dist: groq
Requires-Dist: python-dotenv
Dynamic: author
Dynamic: author-email
Dynamic: classifier
Dynamic: description
Dynamic: description-content-type
Dynamic: home-page
Dynamic: keywords
Dynamic: license-file
Dynamic: project-url
Dynamic: requires-dist
Dynamic: requires-python
Dynamic: summary
